7seg_decoder/7seg_decoder_orig.v
module led7seg(x, a_to_g);

input  wire [3:0] x;
output reg  [6:0] a_to_g;

always @(*)
    case(x)
        4'b0000 : a_to_g<=7'b0000001;    //Display 0
        4'b0001 : a_to_g<=7'b1001111;    //Display 1
        4'b0010 : a_to_g<=7'b0010010;    //Display 2
        4'b0011 : a_to_g<=7'b0000110;    //Display 3
        4'b0100 : a_to_g<=7'b1001100;    //Display 4
        4'b0101 : a_to_g<=7'b0100100;    //Display 5
        4'b0110 : a_to_g<=7'b0100000;    //Display 6
        4'b0111 : a_to_g<=7'b0001111;    //Display 7
        4'b1000 : a_to_g<=7'b0000000;    //Display 8
        4'b1001 : a_to_g<=7'b0001100;    //Display 9
        4'b1010 : a_to_g<=7'b0001000;    //Display A
        4'b1011 : a_to_g<=7'b1100000;    //Display b
        4'b1100 : a_to_g<=7'b0110001;    //Display C
        4'b1101 : a_to_g<=7'b1000010;    //Display d
        4'b1110 : a_to_g<=7'b0110000;    //Display E
        4'b1111 : a_to_g<=7'b0111000;    //Display F
        
    endcase

endmodule

7seg_decoder/7seg_decoder.v
module seg7_decoder(in, a_to_g);

input [3:0] in;
// in[0] = D, in[1] = C, in[2] = B, in[3] = A in your truth table
output [6:0] a_to_g;


assign a_to_g[6] = (~in[3] & ~in[2] & ~in[1] & in[0]) | (~in[3] & in[2] & ~in[1] & ~in[0]) | (in[3] & in[2] & ~in[1] & in[0]) | (in[3] & ~in[2] & in[1] & in[0]);
assign a_to_g[5] = (in[3] & in[1] & in[0]) | (in[2] & in[1] & ~in[0]) | (in[3] & in[2] & ~in[1] & ~in[0]) | (~in[3] & in[2] & ~in[1] & in[0]);
assign a_to_g[4] = (in[3] & in[2] & ~in[0]) | (in[3] & in[2] & in[1]) | (~in[3] & ~in[2] & in[1] & ~in[0]);
assign a_to_g[3] = (~in[3] & in[2] & ~in[1] & ~in[0]) | (~in[2] & ~in[1] & in[0]) | (in[2] & in[1] & in[0]) | (in[3] & ~in[2] & in[1] & ~in[0]);
assign a_to_g[2] = (~in[3] & in[0]) | (~in[2] & ~in[1] & in[0]) | (~in[3] & in[2] & ~in[1]);
assign a_to_g[1] = (~in[3] & ~in[2] & in[0]) | (~in[3] & ~in[2] & in[1]) | (~in[3] & in[1] & in[0]) | (in[3] & in[2] & ~in[1] & in[0]);
assign a_to_g[0] = (~in[3] & ~in[2] & ~in[1]) | (~in[3] & in[2] & in[1] & in[0]) | (in[3] & in[2] & ~in[1] & ~in[0]);
endmodule

7seg_decoder/tb_7seg_decoder.v
`timescale 1ns / 1ps
module tb_led_7seg_decoder;

	// Inputs
	reg [3:0] x;

	// Outputs
	wire [6:0] a_to_g;
    wire [6:0] a_to_g2;

    seg7_decoder uut2(
        .in(x),
        .a_to_g(a_to_g2)
    );


	// Instantiate the Unit Under Test (UUT)
	// leg7seg(x(input), a_to_g(output)))
	led7seg uut (
		.x(x), 
		.a_to_g(a_to_g)
	);

	initial begin
		$dumpfile("tb_led_7seg_decoder.vcd");
		$dumpvars;
		// Initialize Inputs
		x = 0;

		// Wait 100 ns for global reset to finish
		#10;
    	#160 $finish; 
		// Add stimulus here
	
	end

	always @(a_to_g) begin
		// $monitor("benchmark Input:%b, Output:%b\nyour Input:%b, Output:%b", x, a_to_g, x, a_to_g2);
        // if you need print one by one uncomment above and comment below.
        if ( a_to_g == a_to_g2 ) $display("Correct");
        else $display("Error! x=%b \nyour output:%b\nbenchmark:%b", x, a_to_g, a_to_g2);

	end


// 0000
// 0001
// 0010

	always #10 x[0] = ~x[0];
	always #20 x[1] = ~x[1];
	always #40 x[2] = ~x[2];
	always #80 x[3] = ~x[3];
	
	
      
endmodule

7seg_decoder/tb_led_7seg_decoder.vcd
$date
	Sat Nov 11 23:23:43 2023
$end
$version
	Icarus Verilog
$end
$timescale
	1ps
$end
$scope module tb_led_7seg_decoder $end
$var wire 7 ! a_to_g2 [6:0] $end
$var wire 7 " a_to_g [6:0] $end
$var reg 4 # x [3:0] $end
$scope module uut $end
$var wire 4 $ x [3:0] $end
$var reg 7 % a_to_g [6:0] $end
$upscope $end
$scope module uut2 $end
$var wire 4 & in [3:0] $end
$var wire 7 ' a_to_g [6:0] $end
$upscope $end
$upscope $end
$enddefinitions $end
$comment Show the parameter values. $end
$dumpall
$end
#0
$dumpvars
b1 '
b0 &
b1 %
b0 $
b0 #
b1 "
b1 !
$end
#10000
b1001111 "
b1001111 %
b1001111 !
b1001111 '
b1 #
b1 $
b1 &
#20000
b10010 "
b10010 %
b10010 !
b10010 '
b10 #
b10 $
b10 &
#30000
b110 "
b110 %
b110 !
b110 '
b11 #
b11 $
b11 &
#40000
b1001100 "
b1001100 %
b1001100 !
b1001100 '
b100 #
b100 $
b100 &
#50000
b100100 "
b100100 %
b100100 !
b100100 '
b101 #
b101 $
b101 &
#60000
b100000 "
b100000 %
b100000 !
b100000 '
b110 #
b110 $
b110 &
#70000
b1111 "
b1111 %
b1111 !
b1111 '
b111 #
b111 $
b111 &
#80000
b0 "
b0 %
b0 !
b0 '
b1000 #
b1000 $
b1000 &
#90000
b1100 "
b1100 %
b1100 !
b1100 '
b1001 #
b1001 $
b1001 &
#100000
b1000 "
b1000 %
b1000 !
b1000 '
b1010 #
b1010 $
b1010 &
#110000
b1100000 "
b1100000 %
b1100000 !
b1100000 '
b1011 #
b1011 $
b1011 &
#120000
b110001 "
b110001 %
b110001 !
b110001 '
b1100 #
b1100 $
b1100 &
#130000
b1000010 "
b1000010 %
b1000010 !
b1000010 '
b1101 #
b1101 $
b1101 &
#140000
b110000 "
b110000 %
b110000 !
b110000 '
b1110 #
b1110 $
b1110 &
#150000
b111000 "
b111000 %
b111000 !
b111000 '
b1111 #
b1111 $
b1111 &
#160000
b1 "
b1 %
b1 !
b1 '
b0 #
b0 $
b0 &
#170000
b1001111 "
b1001111 %
b1001111 !
b1001111 '
b1 #
b1 $
b1 &
